pacoteMIBC/__init__.py
pacoteMIBC/modulo.py
pacotMIBC-0.0.1.dist-info/LICENSE
pacotMIBC-0.0.1.dist-info/METADATA
pacotMIBC-0.0.1.dist-info/WHEEL
pacotMIBC-0.0.1.dist-info/top_level.txt
pacotMIBC-0.0.1.dist-info/RECORD
