Metadata-Version: 2.1
Name: pacotMIBC
Version: 0.0.1
Summary: Pacote python para exibir número de 1 a 9
Home-page: https://github.com/MIBC/pacoteMIBC
Author: Matheus Iran Boteho Corrêa
Author-email: mathibc03@gmail.com
License: MIT License
Keywords: Pacote
Platform: UNKNOWN
License-File: LICENSE
Requires-Dist: numpy
